odoo/addons/web_widget_text_markdown/README.rst
odoo/addons/web_widget_text_markdown/__init__.py
odoo/addons/web_widget_text_markdown/__manifest__.py
odoo/addons/web_widget_text_markdown/demo/bootstrap_markdown.xml
odoo/addons/web_widget_text_markdown/i18n/ar.po
odoo/addons/web_widget_text_markdown/i18n/de.po
odoo/addons/web_widget_text_markdown/i18n/es.po
odoo/addons/web_widget_text_markdown/i18n/fi.po
odoo/addons/web_widget_text_markdown/i18n/fr.po
odoo/addons/web_widget_text_markdown/i18n/pt_BR.po
odoo/addons/web_widget_text_markdown/i18n/sl.po
odoo/addons/web_widget_text_markdown/i18n/tr.po
odoo/addons/web_widget_text_markdown/i18n/web_widget_text_markdown.pot
odoo/addons/web_widget_text_markdown/readme/CONTRIBUTORS.rst
odoo/addons/web_widget_text_markdown/readme/CREDITS.rst
odoo/addons/web_widget_text_markdown/readme/DESCRIPTION.rst
odoo/addons/web_widget_text_markdown/readme/ROADMAP.rst
odoo/addons/web_widget_text_markdown/readme/USAGE.rst
odoo/addons/web_widget_text_markdown/static/description/icon.png
odoo/addons/web_widget_text_markdown/static/description/index.html
odoo/addons/web_widget_text_markdown/static/src/js/web_widget_text_markdown.js
odoo/addons/web_widget_text_markdown/static/src/less/web_widget_text_markdown.less
odoo/addons/web_widget_text_markdown/static/src/lib/bootstrap-markdown.js
odoo/addons/web_widget_text_markdown/static/src/lib/bootstrap-markdown.min.css
odoo/addons/web_widget_text_markdown/static/src/lib/dropzone.js
odoo/addons/web_widget_text_markdown/static/src/lib/marked.js
odoo/addons/web_widget_text_markdown/static/tests/js/web_widget_text_markdown.js
odoo/addons/web_widget_text_markdown/views/assets.xml
odoo11_addon_web_widget_text_markdown-11.0.1.0.0.99.dev3.dist-info/METADATA
odoo11_addon_web_widget_text_markdown-11.0.1.0.0.99.dev3.dist-info/WHEEL
odoo11_addon_web_widget_text_markdown-11.0.1.0.0.99.dev3.dist-info/top_level.txt
odoo11_addon_web_widget_text_markdown-11.0.1.0.0.99.dev3.dist-info/RECORD
